dagshub/__init__.py
dagshub/logger.py
dagshub/ls_client.py
dagshub/notebook.py
dagshub/py.typed
dagshub/repo_bucket.py
dagshub/auth/__init__.py
dagshub/auth/oauth.py
dagshub/auth/token_auth.py
dagshub/auth/tokens.py
dagshub/colab/__init__.py
dagshub/colab/login.py
dagshub/common/__init__.py
dagshub/common/analytics.py
dagshub/common/cli.py
dagshub/common/config.py
dagshub/common/determine_repo.py
dagshub/common/download.py
dagshub/common/environment.py
dagshub/common/errors.py
dagshub/common/helpers.py
dagshub/common/init.py
dagshub/common/logging_util.py
dagshub/common/notebook.py
dagshub/common/rich_util.py
dagshub/common/tracing.py
dagshub/common/util.py
dagshub/common/api/__init__.py
dagshub/common/api/repo.py
dagshub/common/api/responses.py
dagshub/common/api/user.py
dagshub/data_engine/__init__.py
dagshub/data_engine/datasets.py
dagshub/data_engine/datasources.py
dagshub/data_engine/dtypes.py
dagshub/data_engine/annotation/__init__.py
dagshub/data_engine/annotation/importer.py
dagshub/data_engine/annotation/metadata.py
dagshub/data_engine/annotation/voxel_conversion.py
dagshub/data_engine/client/__init__.py
dagshub/data_engine/client/data_client.py
dagshub/data_engine/client/gql_introspections.py
dagshub/data_engine/client/gql_mutations.py
dagshub/data_engine/client/gql_queries.py
dagshub/data_engine/client/models.py
dagshub/data_engine/client/loaders/__init__.py
dagshub/data_engine/client/loaders/base.py
dagshub/data_engine/client/loaders/tf.py
dagshub/data_engine/client/loaders/torch.py
dagshub/data_engine/client/query_builder/__init__.py
dagshub/data_engine/model/__init__.py
dagshub/data_engine/model/datapoint.py
dagshub/data_engine/model/datasource.py
dagshub/data_engine/model/datasource_state.py
dagshub/data_engine/model/errors.py
dagshub/data_engine/model/metadata_field_builder.py
dagshub/data_engine/model/query.py
dagshub/data_engine/model/query_result.py
dagshub/data_engine/model/schema_util.py
dagshub/data_engine/model/metadata/__init__.py
dagshub-0.6.5.dist-info/licenses/LICENSE
dagshub-0.6.5.dist-info/METADATA
dagshub-0.6.5.dist-info/WHEEL
dagshub-0.6.5.dist-info/entry_points.txt
dagshub-0.6.5.dist-info/top_level.txt
dagshub-0.6.5.dist-info/RECORD
