Metadata-Version: 2.4
Name: dagshub
Version: 0.6.5
Summary: DagsHub client libraries
Home-page: https://github.com/DagsHub/client
Author: DagsHub
Author-email: contact@dagshub.com
Classifier: Programming Language :: Python :: 3
Classifier: License :: OSI Approved :: MIT License
Classifier: Operating System :: OS Independent
Requires-Python: >=3.9
License-File: LICENSE
Requires-Dist: PyYAML>=5
Requires-Dist: appdirs>=1.4.4
Requires-Dist: click>=8.0.4
Requires-Dist: httpx>=0.23.0
Requires-Dist: GitPython>=3.1.29
Requires-Dist: rich>=13.1.0
Requires-Dist: dacite~=1.6.0
Requires-Dist: tenacity>=8.2.2
Requires-Dist: gql[requests]
Requires-Dist: dataclasses-json
Requires-Dist: pandas
Requires-Dist: treelib>=1.6.4
Requires-Dist: pathvalidate>=3.0.0
Requires-Dist: python-dateutil
Requires-Dist: boto3
Requires-Dist: semver
Requires-Dist: dagshub-annotation-converter>=0.1.12
Provides-Extra: jupyter
Requires-Dist: rich[jupyter]>=13.1.0; extra == "jupyter"
Provides-Extra: fuse
Requires-Dist: fusepy>=3; extra == "fuse"
Provides-Extra: autolabeling
Requires-Dist: ngrok>=1.3.0; extra == "autolabeling"
Requires-Dist: cloudpickle>=3.0.0; extra == "autolabeling"
Dynamic: author
Dynamic: author-email
Dynamic: classifier
Dynamic: description
Dynamic: description-content-type
Dynamic: home-page
Dynamic: license-file
Dynamic: provides-extra
Dynamic: requires-dist
Dynamic: requires-python
Dynamic: summary
